mcp_salesforce/__init__.py
mcp_salesforce/server.py
mcp_salesforce-0.1.3.dist-info/METADATA
mcp_salesforce-0.1.3.dist-info/WHEEL
mcp_salesforce-0.1.3.dist-info/entry_points.txt
mcp_salesforce-0.1.3.dist-info/RECORD
