Metadata-Version: 2.4
Name: mcp-salesforce
Version: 0.1.3
Summary: MCP server for Salesforce
Project-URL: Homepage, https://github.com/oliviergg/mcp-salesforce
Author-email: Olivier GG <olivier.gosse.gardet@gmail.com>
License: MIT
Keywords: llm,mcp,salesforce
Requires-Python: >=3.10
Requires-Dist: mcp
Requires-Dist: python-dotenv
Requires-Dist: simple-salesforce
